xray/__init__.py
xray/common.py
xray/components.py
xray/exceptions.py
xray/general_settings.py
xray/issues.py
xray/scanning.py
xray/summary.py
xray/system.py
xray/utils/__init__.py
xray/utils/env.py
xray/utils/http.py
jfrog_xray_api-0.0.6.dist-info/LICENSE
jfrog_xray_api-0.0.6.dist-info/METADATA
jfrog_xray_api-0.0.6.dist-info/WHEEL
jfrog_xray_api-0.0.6.dist-info/top_level.txt
jfrog_xray_api-0.0.6.dist-info/RECORD
