Metadata-Version: 2.1
Name: jfrog-xray-api
Version: 0.0.6
Summary: Python wrapper for JFROG Xray REST API
Author-email: Donghui Wang <977675308@qq.com>
Project-URL: homepage, https://github.com/donhui/jfrog-xray-api
Project-URL: repository, https://github.com/donhui/jfrog-xray-api.git
Project-URL: Bug Tracker, https://github.com/donhui/jfrog-xray-api/issues
Keywords: jfrog,xray,jfrog-xray,devsecops
Classifier: Development Status :: 2 - Pre-Alpha
Classifier: Programming Language :: Python :: 3
Classifier: License :: OSI Approved :: MIT License
Classifier: Operating System :: OS Independent
Classifier: Topic :: Software Development
Requires-Python: >=3.7
License-File: LICENSE
Requires-Dist: requests
Provides-Extra: pylint
Requires-Dist: pylint ; extra == 'pylint'
